odoo/addons/extendable_fastapi/README.rst
odoo/addons/extendable_fastapi/__init__.py
odoo/addons/extendable_fastapi/__manifest__.py
odoo/addons/extendable_fastapi/i18n/extendable_fastapi.pot
odoo/addons/extendable_fastapi/models/__init__.py
odoo/addons/extendable_fastapi/models/fastapi_endpoint.py
odoo/addons/extendable_fastapi/readme/CONTRIBUTORS.rst
odoo/addons/extendable_fastapi/readme/DESCRIPTION.rst
odoo/addons/extendable_fastapi/static/description/icon.png
odoo/addons/extendable_fastapi/static/description/index.html
odoo/addons/extendable_fastapi/tests/__init__.py
odoo/addons/extendable_fastapi/tests/common.py
odoo14_addon_extendable_fastapi-14.0.1.0.1.dist-info/METADATA
odoo14_addon_extendable_fastapi-14.0.1.0.1.dist-info/WHEEL
odoo14_addon_extendable_fastapi-14.0.1.0.1.dist-info/top_level.txt
odoo14_addon_extendable_fastapi-14.0.1.0.1.dist-info/RECORD
