Metadata-Version: 2.1
Name: odoo14-addon-extendable-fastapi
Version: 14.0.1.0.1
Summary: Allows the use of extendable into fastapi apps
Home-page: https://github.com/OCA/rest-framework
Author: ACSONE SA/NV,Odoo Community Association (OCA)
Author-email: support@odoo-community.org
License: LGPL-3
Platform: UNKNOWN
Classifier: Programming Language :: Python
Classifier: Framework :: Odoo
Classifier: Framework :: Odoo :: 14.0
Classifier: License :: OSI Approved :: GNU Lesser General Public License v3 (LGPLv3)
Requires-Python: >=3.8
Requires-Dist: extendable-pydantic (>=0.0.4)
Requires-Dist: odoo14-addon-extendable
Requires-Dist: odoo14-addon-fastapi
Requires-Dist: odoo (<14.1dev,>=14.0a)
